LICENSE
MANIFEST.in
README.md
install_script.py
setup.py
kdYoudaoDictionary/__init__.py
kdYoudaoDictionary/appKey_config.json
kdYoudaoDictionary/fileutil.py
kdYoudaoDictionary/from_to_type.py
kdYoudaoDictionary/kdYoudaoDictionary.py
kdYoudaoDictionary/kdYoudaoDictionary.ui
kdYoudaoDictionary.egg-info/PKG-INFO
kdYoudaoDictionary.egg-info/SOURCES.txt
kdYoudaoDictionary.egg-info/dependency_links.txt
kdYoudaoDictionary.egg-info/entry_points.txt
kdYoudaoDictionary.egg-info/not-zip-safe
kdYoudaoDictionary.egg-info/requires.txt
kdYoudaoDictionary.egg-info/top_level.txt
kdYoudaoDictionary/data/Dictionary-icon.png